tpkasa/__init__.py
tpkasa-0.4.dist-info/METADATA
tpkasa-0.4.dist-info/WHEEL
tpkasa-0.4.dist-info/top_level.txt
tpkasa-0.4.dist-info/RECORD
